autonav/GTRS.py
autonav/WLS.py
autonav/__init__.py
autonav/file_handlers.py
autonav/metrics.py
autonav/plots.py
autonav/random_generator.py
autonav/velocity.py
autonav-1.0.3.dist-info/LICENSE.txt
autonav-1.0.3.dist-info/METADATA
autonav-1.0.3.dist-info/WHEEL
autonav-1.0.3.dist-info/top_level.txt
autonav-1.0.3.dist-info/RECORD
