Metadata-Version: 2.1
Name: autonav
Version: 1.0.3
Summary: Research software for navigating a UAV in indoor environments
Author-email: "Ricardo S. Santos" <p6221@ulusofona.pt>
License: MIT
Project-URL: Bug Reports, https://github.com/ricardo-s-santos/AutoNAV/issues
Project-URL: Documentation, https://ricardo-s-santos.github.io/AutoNAV/
Project-URL: Source, https://github.com/ricardo-s-santos/AutoNAV
Keywords: UAV,Navigation,Indoor
Classifier: Development Status :: 5 - Production/Stable
Classifier: Programming Language :: Python :: 3
Classifier: Intended Audience :: Science/Research
Classifier: License :: OSI Approved :: MIT License
Classifier: Operating System :: OS Independent
Classifier: Topic :: Scientific/Engineering
Requires-Python: >=3.8
License-File: LICENSE.txt
Requires-Dist: numpy >=1.24
Requires-Dist: matplotlib >=3.7.0
Requires-Dist: scipy >=1.10
Provides-Extra: devel
Requires-Dist: isort ; extra == 'devel'
Requires-Dist: black ; extra == 'devel'
Requires-Dist: flake8 ; extra == 'devel'
Requires-Dist: flake8-isort ; extra == 'devel'
Requires-Dist: flake8-black ; extra == 'devel'
Requires-Dist: flake8-bugbear ; extra == 'devel'
Requires-Dist: Flake8-pyproject ; extra == 'devel'
Requires-Dist: mypy ; extra == 'devel'
Requires-Dist: pre-commit ; extra == 'devel'
Requires-Dist: pytest >=7.0 ; extra == 'devel'
Requires-Dist: pytest-cov ; extra == 'devel'
Requires-Dist: pytest-mypy ; extra == 'devel'
Requires-Dist: coverage ; extra == 'devel'
Requires-Dist: mkdocs-material >=7.1.11 ; extra == 'devel'
Requires-Dist: mkdocstrings[python] >=0.19.0 ; extra == 'devel'
Requires-Dist: mkdocs-gallery ; extra == 'devel'
